pcurvepy2/__init__.py
pcurvepy2/pcurve.py
pcurvepy2-0.2.1.dist-info/METADATA
pcurvepy2-0.2.1.dist-info/WHEEL
pcurvepy2-0.2.1.dist-info/licenses/LICENSE
pcurvepy2-0.2.1.dist-info/RECORD
