Metadata-Version: 2.4
Name: pcurvepy2
Version: 0.2.1
Summary: Principal curves implementation in Python
Project-URL: Repository, https://github.com/mossjacob/pcurvepy
Author-email: Jacob Moss <cob.mossy@gmail.com>
License-Expression: MIT
License-File: LICENSE
Requires-Python: >=3.9
Requires-Dist: numpy<3.0.0,>=1.21.0
Requires-Dist: scikit-learn>=1.6.1
Requires-Dist: scipy<2.0.0,>=1.7.0
